kukren/__init__.py
kukren/calculate.py
kukren-0.0.1.dist-info/LICENSE
kukren-0.0.1.dist-info/METADATA
kukren-0.0.1.dist-info/WHEEL
kukren-0.0.1.dist-info/top_level.txt
kukren-0.0.1.dist-info/RECORD
