Metadata-Version: 2.1
Name: kukren
Version: 0.0.1
Summary: simple package calculating for numbers
Home-page: UNKNOWN
Author: piyush patel
Author-email: piyush.patel@colorado.edu
License: UNKNOWN
Keywords: random animal names
Platform: UNKNOWN
Classifier: Programming Language :: Python :: 2
Classifier: Operating System :: OS Independent
